scrapingHelp/__init__.py
scrapingHelp/scrapingHelp.py
scrapingHelp-0.2.5.dist-info/METADATA
scrapingHelp-0.2.5.dist-info/WHEEL
scrapingHelp-0.2.5.dist-info/top_level.txt
scrapingHelp-0.2.5.dist-info/RECORD
