Metadata-Version: 2.2
Name: scrapingHelp
Version: 0.2.5
Summary: # ScrapingHelp
Home-page: https://github.com/brighamturner12/scrapingHelp.git
Author: Brigham Turner
Author-email: brighamturner@narratebay.com
License: MIT
Project-URL: Documentation, https://github.com/brighamturner12/scrapingHelp/blob/main/readme.md
Project-URL: Source Code, https://github.com/brighamturner12/scrapingHelp/blob/main/scrapingHelp.py
Classifier: Programming Language :: Python :: 3
Classifier: License :: OSI Approved :: MIT License
Classifier: Operating System :: OS Independent
Requires-Python: >=3.6
Requires-Dist: bs4
Requires-Dist: lxml
Requires-Dist: lxml
Dynamic: author
Dynamic: author-email
Dynamic: classifier
Dynamic: description
Dynamic: description-content-type
Dynamic: home-page
Dynamic: license
Dynamic: project-url
Dynamic: requires-dist
Dynamic: requires-python
Dynamic: summary
